[
  {
    "showID": 1,
    "dateShow": "2017-02-27T20:00:00",
    "dateDoors": "",
    "dateLots": "",
    "timeZone": "America/Cancun",
    "venue": "Hard Rock Hotel",
    "altName": "Panic en la Play치",
    "notes": "",
    "address": "Km 72, Carretera Cancun-Chetumal",
    "city": "Puerto Aventuras",
    "state": "Q.R.",
    "postal": "77710",
    "country": "Mexico",
    "phoneNbr": "+52-984-875-1100",
    "venueURL": "https://www.hrhrivieramaya.com",
    "setlistURL": "http://www.everydaycompanion.com/setlists/20170227a.asp",
    "seatingURL": "http://panicenlaplaya.com/"
  },
  {
    "showID": 2,
    "dateShow": "2017-02-28T20:00:00",
    "dateDoors": "",
    "dateLots": "",
    "timeZone": "America/Cancun",
    "venue": "Hard Rock Hotel",
    "altName": "Panic en la Play치",
    "notes": "",
    "address": "Km 72, Carretera Cancun-Chetumal",
    "city": "Puerto Aventuras",
    "state": "Q.R.",
    "postal": "77710",
    "country": "Mexico",
    "phoneNbr": "+52-984-875-1100",
    "venueURL": "https://www.hrhrivieramaya.com",
    "setlistURL": "http://www.everydaycompanion.com/setlists/20170228a.asp",
    "seatingURL": "http://panicenlaplaya.com/"
  },
  {
    "showID": 3,
    "dateShow": "2017-03-01T20:00:00",
    "dateDoors": "",
    "dateLots": "",
    "timeZone": "America/Cancun",
    "venue": "Hard Rock Hotel",
    "altName": "Panic en la Play치",
    "notes": "",
    "address": "Km 72, Carretera Cancun-Chetumal",
    "city": "Puerto Aventuras",
    "state": "Q.R.",
    "postal": "77710",
    "country": "Mexico",
    "phoneNbr": "+52-984-875-1100",
    "venueURL": "https://www.hrhrivieramaya.com",
    "setlistURL": "http://www.everydaycompanion.com/setlists/20170301a.asp",
    "seatingURL": "http://panicenlaplaya.com/"
  },
  {
    "showID": 4,
    "dateShow": "2017-03-02T20:00:00",
    "dateDoors": "",
    "dateLots": "",
    "timeZone": "America/Cancun",
    "venue": "Hard Rock Hotel",
    "altName": "Panic en la Play치",
    "notes": "",
    "address": "Km 72, Carretera Cancun-Chetumal",
    "city": "Puerto Aventuras",
    "state": "Q.R.",
    "postal": "77710",
    "country": "Mexico",
    "phoneNbr": "+52-984-875-1100",
    "venueURL": "https://www.hrhrivieramaya.com",
    "setlistURL": "http://www.everydaycompanion.com/setlists/20170302a.asp",
    "seatingURL": "http://panicenlaplaya.com/"
  },
  {
    "showID": 5,
    "dateShow": "2017-04-20T19:30:00",
    "dateDoors": "",
    "dateLots": "",
    "timeZone": "America/New_York",
    "venue": "Spirit of Suwanee Music Park",
    "altName": "Wanee Festival",
    "notes": "",
    "address": "3076 95th Drive",
    "city": "Live Oak",
    "state": "FL",
    "postal": "32060",
    "country": "USA",
    "phoneNbr": "386-364-1683",
    "venueURL": "https://waneefestival.com",
    "setlistURL": "http://www.everydaycompanion.com/setlists/20170420a.asp",
    "seatingURL": "http://waneefestival.com/schedule/"
  },
  {
    "showID": 6,
    "dateShow": "2017-04-22T19:30:00",
    "dateDoors": "",
    "dateLots": "",
    "timeZone": "America/New_York",
    "venue": "Centennial Olympic Park",
    "altName": "Atlanta",
    "notes": "",
    "address": "265 Park Ave W NW",
    "city": "Atlanta",
    "state": "GA",
    "postal": "30313",
    "country": "USA",
    "phoneNbr": "404-223-4412",
    "venueURL": "https://www.sweetwater420fest.com",
    "setlistURL": "http://www.everydaycompanion.com/setlists/20170422a.asp",
    "seatingURL": "http://www.sweetwater420fest.com/"
  },
  {
    "showID": 7,
    "dateShow": "2017-04-23T19:30:00",
    "dateDoors": "",
    "dateLots": "",
    "timeZone": "America/New_York",
    "venue": "Centennial Olympic Park",
    "altName": "Atlanta",
    "notes": "",
    "address": "265 Park Ave W NW",
    "city": "Atlanta",
    "state": "GA",
    "postal": "30313",
    "country": "USA",
    "phoneNbr": "404-223-4412",
    "venueURL": "https://www.sweetwater420fest.com",
    "setlistURL": "http://www.everydaycompanion.com/setlists/20170423a.asp",
    "seatingURL": "http://www.sweetwater420fest.com/"
  },
  {
    "showID": 8,
    "dateShow": "2017-05-04T19:30:00",
    "dateDoors": "",
    "dateLots": "",
    "timeZone": "America/Chicago",
    "venue": "Fair Grounds Race Course",
    "altName": "Jazz Fest",
    "notes": "",
    "address": "1751 Gentilly Blvd",
    "city": "New Orleans",
    "state": "LA",
    "postal": "70119",
    "country": "USA",
    "phoneNbr": "504-944-5515",
    "venueURL": "https://www.nojazzfest.com",
    "setlistURL": "http://www.everydaycompanion.com/setlists/20170504a.asp",
    "seatingURL": "http://9xzxv1eo7572295fo1ebb5x1.wpengine.netdna-cdn.com/wp-content/uploads/2013/01/2016-Fantasy-Map-1.jpg"
  },
  {
    "showID": 9,
    "dateShow": "2017-07-14T19:30:00",
    "dateDoors": "",
    "dateLots": "",
    "timeZone": "America/Chicago",
    "venue": "Sloss Furnaces",
    "altName": "Birmingham",
    "notes": "Sloss Fest",
    "address": "20 32nd Street N",
    "city": "Birmingham",
    "state": "AL",
    "postal": "35222",
    "country": "USA",
    "phoneNbr": "205-324-1911",
    "venueURL": "http://slossfest.com/",
    "setlistURL": "http://www.everydaycompanion.com/setlists/20170714a.asp",
    "seatingURL": "http://slossfest.com/lineup/"
  },
  {
    "showID": 10,
    "dateShow": "2017-07-14T19:30:00",
    "dateDoors": "",
    "dateLots": "",
    "timeZone": "America/Chicago",
    "venue": "Sloss Furnaces",
    "altName": "Birmingham",
    "notes": "Sloss Fest",
    "address": "20 32nd Street N",
    "city": "Birmingham",
    "state": "AL",
    "postal": "35222",
    "country": "USA",
    "phoneNbr": "205-324-1911",
    "venueURL": "http://slossfest.com/",
    "setlistURL": "http://www.everydaycompanion.com/setlists/20170714a.asp",
    "seatingURL": "http://slossfest.com/lineup/"
  },
  {
    "showID": 11,
    "dateShow": "2017-08-26T19:30:00",
    "dateDoors": "",
    "dateLots": "",
    "timeZone": "America/New_York",
    "venue": "Oak Ridge Farm",
    "altName": "Lockn'",
    "notes": "",
    "address": "1510 Diggs Mountain Road",
    "city": "Arrington",
    "state": "VA",
    "postal": "22922",
    "country": "USA",
    "phoneNbr": "",
    "venueURL": "http://www.locknfestival.com/",
    "setlistURL": "http://www.everydaycompanion.com/setlists/20170826a.asp",
    "seatingURL": "http://www.locknfestival.com/wp-content/uploads/lockn_festivalMap_websiteImage_v14.png"
  },
  {
    "showID": 12,
    "dateShow": "2017-08-27T19:30:00",
    "dateDoors": "",
    "dateLots": "",
    "timeZone": "America/New_York",
    "venue": "Oak Ridge Farm",
    "altName": "Lockn'",
    "notes": "",
    "address": "1510 Diggs Mountain Road",
    "city": "Arrington",
    "state": "VA",
    "postal": "22922",
    "country": "USA",
    "phoneNbr": "",
    "venueURL": "http://www.locknfestival.com/",
    "setlistURL": "http://www.everydaycompanion.com/setlists/20170827a.asp",
    "seatingURL": "http://www.locknfestival.com/wp-content/uploads/lockn_festivalMap_websiteImage_v14.png"
  }
]
