[
  {
    "showID": 0,
    "dateShow": "2022-10-01T20:45:00",
    "dateDoors": "2022-10-01T12:00:00",
    "dateLots": "",
    "timeZone": "America/Chicago",
    "venue": "Radians Amphitheatre",
    "altName": "Memphis",
    "notes": "Mempho Music Festival",
    "address": "750 Cherry Rd",
    "city": "Memphis",
    "state": "TN",
    "postal": "38117",
    "country": "USA",
    "phoneNbr": "901-636-4100",
    "venueURL": "https://www.memphofest.com/",
    "setlistURL": "http://www.everydaycompanion.com/setlists/20221001a.asp",
    "seatingURL": "https://static.wixstatic.com/media/dd05a3_3db4ffce902d42e79d0235007c97d3e9~mv2.png/v1/fill/w_1962,h_2548,al_c,q_95,usm_0.66_1.00_0.01,enc_auto/Mempho-Map_2022_v8Digital.png",
    "lat": "35.1117787",
    "lng": "-89.9146806",
    "confidence": "1",
    "placesPhotoReference": "AcYSjRiQkv40JZENagZWKhuYUVMjNoo8_gS3rOf0LgLDxR84K8fDp2QDJDzwgGiv-JHyzBqPQms8xErFGGvnDt7pPpDUB5Sq5AAL_xl3QQ__diNr0a6rAfe8KQD0eWrRbDGADz_yX0NV4A8k7fhVv3KWNrKDOqmxLtu2CwQ3rv8pjbpDUb99",
    "placesID": "ChIJ80_mJRqEf4gRaD7FnK4JmvM",
    "dateString": "1",
    "monthString": "Oct",
    "title": "Sat, Oct 1",
    "YYYYMMDD": "20221001"
  },
  {
    "showID": 1,
    "dateShow": "2022-10-02T19:00:00",
    "dateDoors": "2022-10-02T12:00:00",
    "dateLots": "",
    "timeZone": "America/Chicago",
    "venue": "Radians Amphitheatre",
    "altName": "Memphis",
    "notes": "Mempho Music Festival",
    "address": "750 Cherry Rd",
    "city": "Memphis",
    "state": "TN",
    "postal": "38117",
    "country": "USA",
    "phoneNbr": "901-636-4100",
    "venueURL": "https://www.memphofest.com/",
    "setlistURL": "http://www.everydaycompanion.com/setlists/20221002a.asp",
    "seatingURL": "https://static.wixstatic.com/media/dd05a3_3db4ffce902d42e79d0235007c97d3e9~mv2.png/v1/fill/w_1962,h_2548,al_c,q_95,usm_0.66_1.00_0.01,enc_auto/Mempho-Map_2022_v8Digital.png",
    "lat": "35.1117787",
    "lng": "-89.9146806",
    "confidence": "1",
    "placesPhotoReference": "AcYSjRjgnSS0WCE1CwUltFe6UxJKV0tHFSQ2eiw508i5NYgOWfi1aeMMTUxkH8NfI9Dp2yfCG6KtI5tuXIH7cb-TSkP_KAmgGscjUsycTvhDR5rApUG6XCyVP-pILQcEVl5bgCAcgJN7GOdZ0VgfEC7uSP2aKJarDXJsykcqZnS0ABK3njmJ",
    "placesID": "ChIJ80_mJRqEf4gRaD7FnK4JmvM",
    "dateString": "2",
    "monthString": "Oct",
    "title": "Sun, Oct 2",
    "YYYYMMDD": "20221002"
  },
  {
    "showID": 2,
    "dateShow": "2022-10-21T20:00:00",
    "dateDoors": "2022-10-21T19:00:00",
    "dateLots": "",
    "timeZone": "America/Chicago",
    "venue": "The Riverside Theater",
    "altName": "Milwaukee",
    "notes": "Capacity: 2.450",
    "address": "116 W Wisconsin Ave",
    "city": "Milwaukee",
    "state": "WI",
    "postal": "503203",
    "country": "USA",
    "phoneNbr": "414-242-8200",
    "venueURL": "https://www.pabsttheatergroup.com/venue/the-riverside-theater/",
    "setlistURL": "http://www.everydaycompanion.com/setlists/20221021a.asp",
    "seatingURL": "http://theitourapp.com/data/GA.png",
    "lat": "43.0389097",
    "lng": "-87.9109363",
    "confidence": "1",
    "placesPhotoReference": "AcYSjRi8B0MrZxqU6XIr8lTt-pBv_OZmXAupLZdrrW6G8GWhLS5KvLJMdSD_hY-M5_myvB6Xj0PxnVJbVcp_k1AjlzwG02NrWqjbscn-bsGhm3lHhX8ozFwuzS3gB6Swo98UDM5_fWx8sd-Z7x0ssAK7dqALOhHxlg334z2i5X7w4fnTVKUR",
    "placesID": "ChIJa5H5_wkZBYgRUsC7EMJVvh0",
    "dateString": "21",
    "monthString": "Oct",
    "title": "Fri, Oct 21",
    "YYYYMMDD": "20221021"
  },
  {
    "showID": 3,
    "dateShow": "2022-10-22T20:00:00",
    "dateDoors": "2022-10-22T19:00:00",
    "dateLots": "",
    "timeZone": "America/Chicago",
    "venue": "The Riverside Theater",
    "altName": "Milwaukee",
    "notes": "Capacity: 2.450",
    "address": "116 W Wisconsin Ave",
    "city": "Milwaukee",
    "state": "WI",
    "postal": "503203",
    "country": "USA",
    "phoneNbr": "414-242-8200",
    "venueURL": "https://www.pabsttheatergroup.com/venue/the-riverside-theater/",
    "setlistURL": "http://www.everydaycompanion.com/setlists/20221022a.asp",
    "seatingURL": "http://theitourapp.com/data/GA.png",
    "lat": "43.0389097",
    "lng": "-87.9109363",
    "confidence": "1",
    "placesPhotoReference": "AcYSjRhENR_m3S07JUI-syuuzCDp1-pKiu_JoxyrvIHr4b_ZQe-gDa68iDxpZPfWgCMqAN3kxR0WEdu6faKll4YUit3wDFtLTNVhoT-6OVefnXObQTjgE8ls_VPuukE168ltD_u0rYjUSqTcprtKrq1DZqRx6-lVUVB7DOHuX_CC4coapx_y",
    "placesID": "ChIJa5H5_wkZBYgRUsC7EMJVvh0",
    "dateString": "22",
    "monthString": "Oct",
    "title": "Sat, Oct 22",
    "YYYYMMDD": "20221022"
  },
  {
    "showID": 4,
    "dateShow": "2022-10-23T20:00:00",
    "dateDoors": "2022-10-23T19:00:00",
    "dateLots": "",
    "timeZone": "America/Chicago",
    "venue": "The Riverside Theater",
    "altName": "Milwaukee",
    "notes": "Capacity: 2.450",
    "address": "116 W Wisconsin Ave",
    "city": "Milwaukee",
    "state": "WI",
    "postal": "503203",
    "country": "USA",
    "phoneNbr": "414-242-8200",
    "venueURL": "https://www.pabsttheatergroup.com/venue/the-riverside-theater/",
    "setlistURL": "http://www.everydaycompanion.com/setlists/20221023a.asp",
    "seatingURL": "http://theitourapp.com/data/GA.png",
    "lat": "43.0389097",
    "lng": "-87.9109363",
    "confidence": "1",
    "placesPhotoReference": "AcYSjRgjLwfqVqUbo_0-9AIgDFY_gypdxS7reva6DRr6_LGDKgKSchFip-OAQPkFHTQIJNXCfxF9UKXjQsV6OD2S2AbApVkw5U9Z3Tpp0YqPmlJWpet3mYz1UQNj4p4iCAmUqtx7rQmwdDaLsw6oFnLtSglLmTzW4_oKflxOFiEAWhYeRSGU",
    "placesID": "ChIJa5H5_wkZBYgRUsC7EMJVvh0",
    "dateString": "23",
    "monthString": "Oct",
    "title": "Sun, Oct 23",
    "YYYYMMDD": "20221023"
  },
  {
    "showID": 5,
    "dateShow": "2022-10-28T20:00:00",
    "dateDoors": "2022-10-28T19:00:00",
    "dateLots": "",
    "timeZone": "America/New_York",
    "venue": "Enmarket Arena",
    "altName": "Savannah",
    "notes": "",
    "address": "620 Stiles Ave",
    "city": "Savannah",
    "state": "GA",
    "postal": "31415",
    "country": "USA",
    "phoneNbr": "912-468-5177",
    "venueURL": "https://enmarketarena.com/",
    "setlistURL": "http://www.everydaycompanion.com/setlists/20221028a.asp",
    "seatingURL": "https://maps.ticketmaster.com/maps/geometry/3/event/0E005CFCDA5F6CBA/staticImage?type=png&systemId=HOST",
    "lat": "32.0740493",
    "lng": "-81.11158069999999",
    "confidence": "1",
    "placesPhotoReference": "AcYSjRh5NPxIY7segPhfaMlKKkr2YoHluj8GCbDJjUUll8F9HTqupmb6FW8yxD1_YcF4Kp8ZUyoYmlfl2DgVj0f5TfgpWla_GyM3EF-CRG7VUCpYSvROvRTdfbEbNaUrhhNohZxUEEsbTAdKQIlwQ5mBC4kUVA37GXbJIJCb_w0Q9TSVUTd7",
    "placesID": "ChIJqzQLsxKf-4gRuHGgkDdghIU",
    "dateString": "28",
    "monthString": "Oct",
    "title": "Fri, Oct 28",
    "YYYYMMDD": "20221028"
  },
  {
    "showID": 6,
    "dateShow": "2022-10-29T20:00:00",
    "dateDoors": "2022-10-29T19:00:00",
    "dateLots": "",
    "timeZone": "America/New_York",
    "venue": "Enmarket Arena",
    "altName": "Savannah",
    "notes": "",
    "address": "620 Stiles Ave",
    "city": "Savannah",
    "state": "GA",
    "postal": "31415",
    "country": "USA",
    "phoneNbr": "912-468-5177",
    "venueURL": "https://enmarketarena.com/",
    "setlistURL": "http://www.everydaycompanion.com/setlists/20221029a.asp",
    "seatingURL": "https://maps.ticketmaster.com/maps/geometry/3/event/0E005CFCDA5F6CBA/staticImage?type=png&systemId=HOST",
    "lat": "32.0740493",
    "lng": "-81.11158069999999",
    "confidence": "1",
    "placesPhotoReference": "AcYSjRhJb8p75UHLHx4jorRspC7iyg5Q-u97WzeRwRyofN4WHxC_ic3t_DnaycY9Y9UNp8r9q-1nJOCPJIeKa8IvPEEXJrd9QNwhaB9U2UPZKrN02i2-3c6OIUud-SbX1HeLSEnD3K_VI2qpB_np-hZYPJfbbmF6Gj7BBEzIH2Uk-94AD0rQ",
    "placesID": "ChIJqzQLsxKf-4gRuHGgkDdghIU",
    "dateString": "29",
    "monthString": "Oct",
    "title": "Sat, Oct 29",
    "YYYYMMDD": "20221029"
  },
  {
    "showID": 100,
    "dateShow": "2022-12-30T20:00:00",
    "dateDoors": "2022-12-30T18:30:00",
    "dateLots": "",
    "timeZone": "America/Chicago",
    "venue": "Bridgestone Arena",
    "altName": "Nashville",
    "notes": "Capacity: 19,891",
    "address": "501 Broadway",
    "city": "Nashville",
    "state": "TN",
    "postal": "37203",
    "country": "USA",
    "phoneNbr": "615-770-2000",
    "venueURL": "https://www.bridgestonearena.com/",
    "setlistURL": "http://www.everydaycompanion.com/setlists/20221230a.asp",
    "seatingURL": "https://maps.ticketmaster.com/maps/geometry/3/event/1B005D309E4E678F/staticImage?type=png&systemId=HOST",
    "lat": "36.1591736",
    "lng": "-86.7784959",
    "confidence": "1",
    "placesPhotoReference": "AcYSjRgu4dUEG1DE8BTAR7z8YrMmyPsniin1WyorqOT-ao2zWFMd_Z6Lbk0FHoFI3jeeVrsvlcbyEIZTePkqcLByJvhj9K_6WgnVw-SOKMqL9GyqrwepU8GKNJKCZWg2RXKA-ngmN79nZm9HvP9-Ot2nzlF7bu648Et62ZT6x2yWCAFb59Oa",
    "placesID": "ChIJR2SNw15mZIgREmY_zX5TAKk",
    "dateString": "30",
    "monthString": "Dec",
    "title": "Fri, Dec 30",
    "YYYYMMDD": "20221230"
  },
  {
    "showID": 101,
    "dateShow": "2022-12-31T20:00:00",
    "dateDoors": "2022-12-31T18:30:00",
    "dateLots": "",
    "timeZone": "America/Chicago",
    "venue": "Bridgestone Arena",
    "altName": "Nashville",
    "notes": "Capacity: 19,891",
    "address": "501 Broadway",
    "city": "Nashville",
    "state": "TN",
    "postal": "37203",
    "country": "USA",
    "phoneNbr": "615-770-2000",
    "venueURL": "https://www.bridgestonearena.com/",
    "setlistURL": "http://www.everydaycompanion.com/setlists/20221231a.asp",
    "seatingURL": "https://maps.ticketmaster.com/maps/geometry/3/event/1B005D309E4E678F/staticImage?type=png&systemId=HOST",
    "lat": "36.1591736",
    "lng": "-86.7784959",
    "confidence": "1",
    "placesPhotoReference": "AcYSjRibvlaGuXC7ukcC8Uc7L_vB3gYAFrW9tbcz59XxgjUFIqB8Gsye5pt0oqgWCKPxVe5bg3FnyGGsxeYorbPd9puGzRAlherY8ycBiHOP3HdwRRVv0eg0wBF5eMBm6rRPj-PaghkHo66ZUDmQ2tlxZ5Qg15y65VLV_FoKe1p-1B66tk8K",
    "placesID": "ChIJR2SNw15mZIgREmY_zX5TAKk",
    "dateString": "31",
    "monthString": "Dec",
    "title": "Sat, Dec 31",
    "YYYYMMDD": "20221231"
  },
  {
    "showID": 200,
    "dateShow": "2023-01-14T20:00:00",
    "dateDoors": "",
    "dateLots": "",
    "timeZone": "America/Cancun",
    "venue": "Hard Rock Hotel",
    "altName": "Riviera Maya",
    "notes": "Panic en la Playa 11",
    "address": "Km 72, Carretera Cancun-Chetumal",
    "city": "",
    "state": "Puerto Aventuras",
    "postal": "77710",
    "country": "Mexico",
    "phoneNbr": "561-368-8922",
    "venueURL": "https://www.hrhrivieramaya.com/",
    "setlistURL": "http://www.everydaycompanion.com/setlists/20230114a.asp",
    "seatingURL": "https://panicenlaplaya.com",
    "lat": "20.5070261",
    "lng": "-87.2153574",
    "confidence": "1",
    "placesPhotoReference": "AcYSjRgux41w2vapdyUQ1RKahShTmMiiKejWjDMYDiAp_wQHfSXBASfUxtZf1l2okk22aLJ4rwKarlpswAgVQvyyoaCEPamWJyNwk0ysjH7EzDWc1O7DG9jWciS9vy5Gfe_L2OJgJR5LX06FVatQAIAIrpDC494XqspMsRpWcS8BnFkkVLeS",
    "placesID": "ChIJUXms_7L_zYURc_TDzmbDBpE",
    "dateString": "14",
    "monthString": "Jan",
    "title": "Sat, Jan 14",
    "YYYYMMDD": "20230114"
  },
  {
    "showID": 201,
    "dateShow": "2023-01-15T20:00:00",
    "dateDoors": "",
    "dateLots": "",
    "timeZone": "America/Cancun",
    "venue": "Hard Rock Hotel",
    "altName": "Riviera Maya",
    "notes": "Panic en la Playa 11",
    "address": "Km 72, Carretera Cancun-Chetumal",
    "city": "",
    "state": "Puerto Aventuras",
    "postal": "77710",
    "country": "Mexico",
    "phoneNbr": "561-368-8922",
    "venueURL": "https://www.hrhrivieramaya.com/",
    "setlistURL": "http://www.everydaycompanion.com/setlists/20230115a.asp",
    "seatingURL": "https://panicenlaplaya.com",
    "lat": "20.5070261",
    "lng": "-87.2153574",
    "confidence": "1",
    "placesPhotoReference": "AcYSjRiRX6P8B5Q3eDh6Q9mnWEcfVuR5_SjYc6E5nBCxGLEnQoFulo823iDPwlA86kcSxnuyuXSopLYwN3HwwxYePC4tb6du_CJFvUUBTjByfTT6tdm94rdYa4194dzusJaTpr1VHesqb1STCIqUn4SfQWqJxt-XOWIXUCXtWAzr-36-IGsr",
    "placesID": "ChIJUXms_7L_zYURc_TDzmbDBpE",
    "dateString": "15",
    "monthString": "Jan",
    "title": "Sun, Jan 15",
    "YYYYMMDD": "20230115"
  },
  {
    "showID": 202,
    "dateShow": "2023-01-16T20:00:00",
    "dateDoors": "",
    "dateLots": "",
    "timeZone": "America/Cancun",
    "venue": "Hard Rock Hotel",
    "altName": "Riviera Maya",
    "notes": "Panic en la Playa 11",
    "address": "Km 72, Carretera Cancun-Chetumal",
    "city": "",
    "state": "Puerto Aventuras",
    "postal": "77710",
    "country": "Mexico",
    "phoneNbr": "561-368-8922",
    "venueURL": "https://www.hrhrivieramaya.com/",
    "setlistURL": "http://www.everydaycompanion.com/setlists/20230116a.asp",
    "seatingURL": "https://panicenlaplaya.com",
    "lat": "20.5070261",
    "lng": "-87.2153574",
    "confidence": "1",
    "placesPhotoReference": "AcYSjRjZ6n9eZauIGn6CPv-pa2kacyu1WYR95XS88g7QhxHwTnr1FpbZOOFIjsgccNKlOVOTutULM4JBJj1zyxp5PMyb49jN9bpPbZJYLdCwBnqCTOIUspKZNrMqH5l8nZNlmJ5IX9knF7r4hMwGN7eURlMnPM6wvxR8uFH-6wCaPY8E9fIx",
    "placesID": "ChIJUXms_7L_zYURc_TDzmbDBpE",
    "dateString": "16",
    "monthString": "Jan",
    "title": "Mon, Jan 16",
    "YYYYMMDD": "20230116"
  },
  {
    "showID": 203,
    "dateShow": "2023-01-17T20:00:00",
    "dateDoors": "",
    "dateLots": "",
    "timeZone": "America/Cancun",
    "venue": "Hard Rock Hotel",
    "altName": "Riviera Maya",
    "notes": "Panic en la Playa 11",
    "address": "Km 72, Carretera Cancun-Chetumal",
    "city": "",
    "state": "Puerto Aventuras",
    "postal": "77710",
    "country": "Mexico",
    "phoneNbr": "561-368-8922",
    "venueURL": "https://www.hrhrivieramaya.com/",
    "setlistURL": "http://www.everydaycompanion.com/setlists/20230117a.asp",
    "seatingURL": "https://panicenlaplaya.com",
    "lat": "20.5070261",
    "lng": "-87.2153574",
    "confidence": "1",
    "placesPhotoReference": "AcYSjRjbh4VmMvAEZn8uEah0SfE2uCTm3jHhl3tskI0cpgAGoFsJ9HfFETybebqNcxb-IzlJiphJuy_6Ui3AwpioKzpsKUcxNDpqbb8WBshrPUrUm3Oe7JKXN8lgUNbaCVotG0dEN5y6zfwUduz3ueMj89WwLS5nqncwvQNH1yIbhNbZVAxO",
    "placesID": "ChIJUXms_7L_zYURc_TDzmbDBpE",
    "dateString": "17",
    "monthString": "Jan",
    "title": "Tue, Jan 17",
    "YYYYMMDD": "20230117"
  }
]
