[
  {
    "showID": 1,
    "dateShow": "2017-01-25T20:00:00",
    "dateDoors": "2016-12-28T18:30:00",
    "dateLots": "",
    "timeZone": "America/Chicago",
    "venue": "Smart Financial Centre",
    "altName": "Sugar Land",
    "notes": "An Evening with Dave & Tim",
    "address": "18111 Lexington Blvd",
    "city": "Sugar Land",
    "state": "TX",
    "postal": "77479",
    "country": "USA",
    "phoneNbr": "281-207-6278",
    "venueURL": "http://www.smartfinancialcentre.com",
    "setlistURL": "http://www.antsmarching.org/tour/ViewShow.php?ShowID=4658",
    "seatingURL": "http://s1.ticketm.net/tm/en-us/tmimages/venue/maps/dl2/71567s.gif"
  },
  {
    "showID": 2,
    "dateShow": "2017-01-26T20:30:00",
    "dateDoors": "2016-12-28T18:30:00",
    "dateLots": "",
    "timeZone": "America/Chicago",
    "venue": "Verizon Theatre",
    "altName": "Grand Prairie",
    "notes": "An Evening with Dave & Tim",
    "address": "1001 Performance Pl",
    "city": "Grand Prairie",
    "state": "TX",
    "postal": "75050",
    "country": "USA",
    "phoneNbr": "972-854-5050",
    "venueURL": "http://www.verizontheatre.com/",
    "setlistURL": "http://www.antsmarching.org/tour/ViewShow.php?ShowID=4659",
    "seatingURL": "http://s1.ticketm.net/tm/en-us/tmimages/venue/maps/t43/40392s.gif"
  },
  {
    "showID": 3,
    "dateShow": "2017-02-23T19:00:00",
    "dateDoors": "",
    "dateLots": "",
    "timeZone": "America/Cancun",
    "venue": "Barceló Maya Beach",
    "altName": "Riviera Maya",
    "notes": "An Evening with Dave & Tim",
    "address": "123 Mexico 307",
    "city": "Chacalal",
    "state": "Q.R.",
    "postal": "",
    "country": "Mexico",
    "phoneNbr": "+52 984 875 1500",
    "venueURL": "https://www.barcelo.com",
    "setlistURL": "http://www.antsmarching.org/tour/ViewShow.php?ShowID=4660",
    "seatingURL": "http://daveandtimrivieramaya.com/"
  },
  {
    "showID": 4,
    "dateShow": "2017-02-24T19:00:00",
    "dateDoors": "",
    "dateLots": "",
    "timeZone": "America/Cancun",
    "venue": "Barceló Maya Beach",
    "altName": "Riviera Maya",
    "notes": "An Evening with Dave & Tim",
    "address": "123 Mexico 307",
    "city": "Chacalal",
    "state": "Q.R.",
    "postal": "",
    "country": "Mexico",
    "phoneNbr": "+52 984 875 1500",
    "venueURL": "https://www.barcelo.com",
    "setlistURL": "http://www.antsmarching.org/tour/ViewShow.php?ShowID=4661",
    "seatingURL": "http://daveandtimrivieramaya.com/"
  },
  {
    "showID": 5,
    "dateShow": "2017-02-25T19:00:00",
    "dateDoors": "",
    "dateLots": "",
    "timeZone": "America/Cancun",
    "venue": "Barceló Maya Beach",
    "altName": "Riviera Maya",
    "notes": "An Evening with Dave & Tim",
    "address": "123 Mexico 307",
    "city": "Chacalal",
    "state": "Q.R.",
    "postal": "",
    "country": "Mexico",
    "phoneNbr": "+52 984 875 1500",
    "venueURL": "https://www.barcelo.com",
    "setlistURL": "http://www.antsmarching.org/tour/ViewShow.php?ShowID=4662",
    "seatingURL": "http://daveandtimrivieramaya.com/"
  },
  {
    "showID": 6,
    "dateShow": "2017-03-20T19:30:00",
    "dateDoors": "2017-03-20T18:30:00",
    "dateLots": "",
    "timeZone": "Europe/London",
    "venue": "Eventim Apollo",
    "altName": "London",
    "notes": "An Evening with Dave & Tim",
    "address": "45 Queen Caroline St",
    "city": "",
    "state": "London",
    "postal": "W6 9QH",
    "country": "UK",
    "phoneNbr": "+020 8563 3800",
    "venueURL": "http://www.eventimapollo.com/",
    "setlistURL": "http://www.antsmarching.org/tour/ViewShow.php?ShowID=4663",
    "seatingURL": "http://hammersmithapollo.s3.amazonaws.com/img/SeatingPlan3.jpg"
  },
  {
    "showID": 7,
    "dateShow": "2017-03-21T19:30:00",
    "dateDoors": "2017-03-21T18:30:00",
    "dateLots": "",
    "timeZone": "Europe/London",
    "venue": "Eventim Apollo",
    "altName": "London",
    "notes": "An Evening with Dave & Tim",
    "address": "45 Queen Caroline St",
    "city": "",
    "state": "London",
    "postal": "W6 9QH",
    "country": "UK",
    "phoneNbr": "+020 8563 3800",
    "venueURL": "http://www.eventimapollo.com/",
    "setlistURL": "http://www.antsmarching.org/tour/ViewShow.php?ShowID=4664",
    "seatingURL": "http://hammersmithapollo.s3.amazonaws.com/img/SeatingPlan3.jpg"
  },
  {
    "showID": 8,
    "dateShow": "2017-03-23T19:30:00",
    "dateDoors": "2017-03-23T18:30:00",
    "dateLots": "",
    "timeZone": "Europe/London",
    "venue": "Olympia Theatre",
    "altName": "Dublin",
    "notes": "An Evening with Dave & Tim",
    "address": "72 Dame Street",
    "city": "",
    "state": "Dublin 2",
    "postal": "Ireland",
    "country": "UK",
    "phoneNbr": "+353 1 679 3323",
    "venueURL": "http://olympia.ie/",
    "setlistURL": "http://www.antsmarching.org/tour/ViewShow.php?ShowID=4665",
    "seatingURL": "http://olympia.ie/fs/img/Olympia%20full%20chart%20with%20Stalls%20seating%20new%20layout%20-%20May%202016.jpg"
  },
  {
    "showID": 9,
    "dateShow": "2017-03-25T19:30:00",
    "dateDoors": "2017-03-25T18:30:00",
    "dateLots": "",
    "timeZone": "Europe/Amsterdam",
    "venue": "De Oosterpoort",
    "altName": "Groningen",
    "notes": "An Evening with Dave & Tim",
    "address": "Trompsingel 27",
    "city": "",
    "state": "9724 DA",
    "postal": "Groningen",
    "country": "Netherlands",
    "phoneNbr": "+31 50 368 0368",
    "venueURL": "http://de-oosterpoort.nl",
    "setlistURL": "http://www.antsmarching.org/tour/ViewShow.php?ShowID=4666",
    "seatingURL": "http://www.euro-ticket.com/tickets/stadium/bilety_na_kontserty_netherlands_concert_tickets/zakaz_biletov_groningen_sports_tickets/schema_de_oosterpoort_groningen_seating_plan_images/0/3435/"
  },
  {
    "showID": 10,
    "dateShow": "2017-03-27T20:30:00",
    "dateDoors": "2017-03-27T19:00:00",
    "dateLots": "",
    "timeZone": "Europe/Berlin",
    "venue": "Palladium",
    "altName": "Köln",
    "notes": "An Evening with Dave & Tim",
    "address": "Schanzenstraße 40",
    "city": "",
    "state": "51063 Köln",
    "postal": "",
    "country": "Germany",
    "phoneNbr": "+49 221 96790",
    "venueURL": "http://www.palladium-koeln.de/",
    "setlistURL": "http://www.antsmarching.org/tour/ViewShow.php?ShowID=4667",
    "seatingURL": "http://www.palladium-koeln.de/fileadmin/Inhalte/Downloads/Palladium_Reihenbestuhlung_1332pax.pdf"
  }
]
